pyawr_utils/__init__.py
pyawr_utils/awrde_utils.py
pyawr_utils/common_utils.py
pyawr_utils/graph_utils.py
pyawr_utils/misc_utils.py
pyawr_utils/schematic_utils.py
pyawr_utils/vss_utils.py
pyawr_utils-1.0.dist-info/LICENSE
pyawr_utils-1.0.dist-info/METADATA
pyawr_utils-1.0.dist-info/WHEEL
pyawr_utils-1.0.dist-info/top_level.txt
pyawr_utils-1.0.dist-info/RECORD
