Metadata-Version: 2.1
Name: pyawr-utils
Version: 1.0
Summary: Python Utilities for AWR Design Environment
Home-page: https://kb.awr.com/display/awrscripts/Pyawr+Utilities
Author: AWR
Classifier: Programming Language :: Python :: 3
Classifier: License :: OSI Approved :: MIT License
Classifier: Operating System :: OS Independent
Requires-Python: >=3.9
License-File: LICENSE
Requires-Dist: pyawr
Requires-Dist: numpy
